twitter/__init__.py
twitter/__version__.py
twitter/account.py
twitter/account_profile.py
twitter/constants.py
twitter/login.py
twitter/manager.py
twitter/proxy.py
twitter/scraper.py
twitter/search.py
twitter/util.py
elonpanic-0.0.9.dist-info/LICENSE
elonpanic-0.0.9.dist-info/METADATA
elonpanic-0.0.9.dist-info/WHEEL
elonpanic-0.0.9.dist-info/entry_points.txt
elonpanic-0.0.9.dist-info/top_level.txt
elonpanic-0.0.9.dist-info/RECORD
