Metadata-Version: 2.2
Name: elonpanic
Version: 0.0.9
Summary: Implementation of X/Twitter v1, v2, and GraphQL APIs with proxy support.
Home-page: https://github.com/trevorhobenshield/twitter-api-client
Author: Richard
License: MIT
Classifier: Programming Language :: Python :: 3
Classifier: Programming Language :: Python :: 3.8
Classifier: Programming Language :: Python :: 3.9
Classifier: Programming Language :: Python :: 3.10
Classifier: License :: OSI Approved :: MIT License
Classifier: Operating System :: OS Independent
Classifier: Development Status :: 4 - Beta
Classifier: Intended Audience :: Developers
Classifier: Intended Audience :: Science/Research
Classifier: Topic :: Software Development :: Libraries :: Python Modules
Requires-Python: >=3.8
License-File: LICENSE
Requires-Dist: aiofiles
Requires-Dist: nest_asyncio
Requires-Dist: httpx[socks]==0.28.1
Requires-Dist: pyyaml
Requires-Dist: tqdm
Requires-Dist: orjson
Requires-Dist: m3u8
Requires-Dist: websockets
Requires-Dist: uvloop; platform_system != "Windows"
Dynamic: author
Dynamic: classifier
Dynamic: description
Dynamic: description-content-type
Dynamic: home-page
Dynamic: license
Dynamic: requires-dist
Dynamic: requires-python
Dynamic: summary
